wenbot.py
wenbot-0.0.9.dist-info/LICENSE
wenbot-0.0.9.dist-info/METADATA
wenbot-0.0.9.dist-info/WHEEL
wenbot-0.0.9.dist-info/top_level.txt
wenbot-0.0.9.dist-info/RECORD
