Metadata-Version: 2.1
Name: wenbot
Version: 0.0.9
Summary: Simple bot wrapper of selenium basic functions
Home-page: https://github.com/zhaowb/wenbot.git
Author: Wenbo Zhao
Author-email: zhaowb@gmail.com
License: UNKNOWN
Platform: UNKNOWN
Classifier: Programming Language :: Python :: 3
Classifier: License :: OSI Approved :: MIT License
Classifier: Operating System :: OS Independent
Requires-Python: >=3.6
License-File: LICENSE
Requires-Dist: selenium
Requires-Dist: beautifulsoup4
